{"이미지 정보":{"이미지 식별자":1241986,"이미지 높이":800,"이미지 파일명":"019-286-3,261-39,126-Haemil_194_08.jpg","이미지 너비":800},"데이터셋 정보":{"파일 생성일자":"2020-11-19 16:55:11","데이터셋 상세설명":{"렉트좌표":{"아우터":[{}],"하의":[{}],"원피스":[{}],"상의":[{"X좌표":300.203,"Y좌표":-0.5,"가로":402,"세로":524}]},"폴리곤좌표":{"아우터":[{}],"하의":[{}],"원피스":[{}],"상의":[{"X좌표35":431.703,"X좌표34":466.703,"X좌표33":488.703,"X좌표32":517.703,"X좌표31":548.703,"X좌표30":563.703,"X좌표8":300.703,"X좌표9":304.703,"Y좌표33":11.0,"Y좌표32":0.0,"Y좌표35":5.0,"Y좌표34":14.0,"Y좌표31":34.0,"Y좌표30":33.0,"X좌표2":419.703,"X좌표3":351.703,"X좌표1":431.703,"X좌표6":301.703,"X좌표7":310.703,"X좌표4":331.703,"X좌표5":301.703,"Y좌표26":246.0,"Y좌표25":273.0,"Y좌표28":62.0,"Y좌표9":353.0,"Y좌표27":213.0,"Y좌표22":392.0,"Y좌표21":380.0,"Y좌표24":314.0,"Y좌표23":333.0,"Y좌표20":422.0,"X좌표19":637.703,"X좌표18":596.703,"X좌표17":541.703,"X좌표16":472.703,"X좌표15":401.703,"X좌표14":357.703,"X좌표13":359.703,"X좌표12":328.703,"X좌표11":317.703,"Y좌표4":138.0,"X좌표10":315.703,"Y좌표3":82.0,"Y좌표2":51.0,"Y좌표1":7.0,"Y좌표8":336.0,"Y좌표7":321.0,"Y좌표29":36.0,"Y좌표6":303.0,"Y좌표5":241.0,"Y좌표15":516.0,"Y좌표14":492.0,"Y좌표17":518.0,"Y좌표16":524.0,"Y좌표11":375.0,"Y좌표10":359.0,"Y좌표13":449.0,"Y좌표12":454.0,"X좌표29":606.703,"X좌표28":654.703,"X좌표27":701.703,"X좌표26":702.703,"X좌표25":694.703,"X좌표24":688.703,"X좌표23":677.703,"X좌표22":659.703,"X좌표21":634.703,"X좌표20":636.703,"Y좌표19":491.0,"Y좌표18":505.0}]},"라벨링":{"스타일":[{"스타일":"레트로","서브스타일":"스트리트"}],"아우터":[{}],"하의":[{}],"원피스":[{}],"상의":[{"기장":"노멀","색상":"와인","카테고리":"니트웨어","소매기장":"7부소매","소재":["니트"],"프린트":["무지"],"넥라인":"터틀넥","핏":"노멀"}]}},"파일 번호":1241986,"파일 이름":"019-286-3,261-39,126-Haemil_194_08.jpg"}}