{"이미지 정보":{"이미지 식별자":1232161,"이미지 높이":800,"이미지 파일명":"1-(9)-009-276-4,164-19,041-Forme_325_09.jpg","이미지 너비":800},"데이터셋 정보":{"파일 생성일자":"2020-11-19 16:11:46","데이터셋 상세설명":{"렉트좌표":{"아우터":[{"X좌표":53.0,"Y좌표":25.5,"가로":515,"세로":648}],"하의":[{}],"원피스":[{}],"상의":[{}]},"폴리곤좌표":{"아우터":[{"X좌표35":340.5,"X좌표34":354.5,"X좌표33":344.5,"X좌표32":316.5,"X좌표31":300.5,"X좌표30":276.5,"X좌표8":564.5,"X좌표9":560.5,"Y좌표33":86.0,"Y좌표32":114.0,"Y좌표35":30.0,"Y좌표34":60.0,"Y좌표31":156.0,"Y좌표30":102.0,"X좌표2":369.5,"X좌표3":393.5,"X좌표1":341.5,"X좌표6":555.5,"X좌표7":568.5,"X좌표4":450.5,"X좌표5":499.5,"Y좌표26":75.0,"Y좌표25":95.0,"Y좌표28":26.0,"Y좌표9":506.0,"Y좌표27":67.0,"Y좌표22":510.0,"Y좌표21":532.0,"Y좌표24":141.0,"Y좌표23":438.0,"Y좌표20":544.0,"X좌표19":159.5,"X좌표18":205.5,"X좌표17":290.5,"X좌표16":300.5,"X좌표15":308.5,"X좌표14":356.5,"X좌표13":491.5,"X좌표12":494.5,"X좌표11":485.5,"Y좌표4":69.0,"X좌표10":541.5,"Y좌표3":64.0,"Y좌표2":33.0,"Y좌표1":32.0,"Y좌표8":467.0,"Y좌표7":439.0,"Y좌표29":59.0,"Y좌표6":422.0,"Y좌표5":120.0,"Y좌표15":619.0,"Y좌표14":674.0,"Y좌표17":672.0,"Y좌표16":656.0,"Y좌표11":526.0,"Y좌표10":521.0,"Y좌표13":644.0,"Y좌표12":597.0,"X좌표29":255.5,"X좌표28":257.5,"X좌표27":206.5,"X좌표26":168.5,"X좌표25":139.5,"X좌표24":108.5,"X좌표23":82.5,"X좌표22":53.5,"X좌표21":110.5,"X좌표20":155.5,"Y좌표19":654.0,"Y좌표18":672.0}],"하의":[{}],"원피스":[{}],"상의":[{}]},"라벨링":{"스타일":[{"스타일":"오리엔탈"}],"아우터":[{"기장":"하프","색상":"베이지","카테고리":"재킷","옷깃":"셔츠칼라","소매기장":"7부소매","소재":["린넨"],"프린트":["무지"],"핏":"노멀"}],"하의":[{}],"원피스":[{}],"상의":[{}]}},"파일 번호":1232161,"파일 이름":"1-(9)-009-276-4,164-19,041-Forme_325_09.jpg"}}