{"이미지 정보":{"이미지 식별자":1235549,"이미지 높이":800,"이미지 파일명":"012-279-949-21,968-Prau_020_08.jpg","이미지 너비":800},"데이터셋 정보":{"파일 생성일자":"2020-11-19 16:25:26","데이터셋 상세설명":{"렉트좌표":{"아우터":[{}],"하의":[{}],"원피스":[{}],"상의":[{"X좌표":277.254,"Y좌표":68.4672,"가로":325,"세로":623}]},"폴리곤좌표":{"아우터":[{}],"하의":[{}],"원피스":[{}],"상의":[{"Y좌표9":678.744,"Y좌표21":71.9644,"Y좌표20":71.9644,"X좌표19":390.651,"X좌표18":425.619,"X좌표17":464.583,"X좌표16":469.579,"X좌표15":502.548,"X좌표14":554.501,"X좌표13":578.479,"X좌표12":603.456,"X좌표11":577.48,"Y좌표4":676.746,"X좌표10":552.503,"Y좌표3":485.587,"Y좌표2":207.84,"Y좌표1":74.9617,"Y좌표8":680.742,"Y좌표7":687.736,"Y좌표6":692.731,"Y좌표5":683.74,"Y좌표15":99.9389,"Y좌표14":193.853,"X좌표8":470.578,"Y좌표17":87.9499,"X좌표9":515.537,"Y좌표16":68.9672,"Y좌표11":661.76,"Y좌표10":674.748,"Y좌표13":398.999,"Y좌표12":646.773,"X좌표2":277.754,"X좌표21":324.711,"X좌표3":282.749,"X좌표20":349.688,"X좌표1":333.703,"X좌표6":371.668,"Y좌표19":76.9599,"X좌표7":421.622,"Y좌표18":86.9508,"X좌표4":293.739,"X좌표5":332.703}]},"라벨링":{"스타일":[{"스타일":"소피스트케이티드"}],"아우터":[{}],"하의":[{}],"원피스":[{}],"상의":[{"기장":"노멀","색상":"화이트","카테고리":"블라우스","디테일":["셔링"],"소매기장":"7부소매","소재":["우븐"],"프린트":["무지"],"넥라인":"라운드넥","핏":"노멀"}]}},"파일 번호":1235549,"파일 이름":"012-279-949-21,968-Prau_020_08.jpg"}}