{"이미지 정보":{"이미지 식별자":649888,"이미지 높이":1066,"이미지 파일명":"1 (15048).jpg","이미지 너비":800},"데이터셋 정보":{"파일 생성일자":"2020-10-27 17:52:01","데이터셋 상세설명":{"렉트좌표":{"아우터":[{}],"하의":[{}],"원피스":[{"X좌표":215.5,"Y좌표":643.258,"가로":289,"세로":415}],"상의":[{}]},"폴리곤좌표":{"아우터":[{}],"하의":[{}],"원피스":[{"Y좌표9":866.675,"Y좌표22":676.746,"Y좌표21":731.725,"Y좌표24":643.758,"Y좌표23":650.756,"Y좌표20":763.713,"X좌표19":216.0,"X좌표18":228.0,"X좌표17":271.0,"X좌표16":252.0,"X좌표15":249.0,"X좌표14":237.0,"X좌표13":483.0,"X좌표12":480.0,"X좌표11":465.0,"Y좌표4":651.755,"X좌표10":443.0,"Y좌표3":650.756,"Y좌표2":728.726,"Y좌표1":643.758,"Y좌표8":831.688,"Y좌표7":801.699,"Y좌표6":782.706,"Y좌표5":705.735,"Y좌표15":951.643,"Y좌표14":1056.6,"X좌표8":504.0,"Y좌표17":874.672,"X좌표9":469.0,"Y좌표16":924.653,"Y좌표11":919.655,"Y좌표10":860.677,"Y좌표13":1059.6,"Y좌표12":978.633,"X좌표24":324.0,"X좌표23":288.0,"X좌표22":261.0,"X좌표2":367.0,"X좌표21":248.0,"X좌표3":436.0,"X좌표20":229.0,"X좌표1":320.0,"X좌표6":505.0,"Y좌표19":815.694,"X좌표7":500.0,"Y좌표18":867.674,"X좌표4":468.0,"X좌표5":497.0}],"상의":[{}]},"라벨링":{"스타일":[{"스타일":"섹시"}],"아우터":[{}],"하의":[{}],"원피스":[{"기장":"미니","색상":"화이트","서브색상":"블랙","카테고리":"드레스","디테일":["셔링"],"소매기장":"긴팔","소재":["시폰"],"프린트":["호피"],"넥라인":"브이넥","핏":"노멀"}],"상의":[{}]}},"파일 번호":649888,"파일 이름":"1 (15048).jpg"}}