{"이미지 정보":{"이미지 식별자":1315353,"이미지 높이":600,"이미지 파일명":"1 (27082).JPG","이미지 너비":800},"데이터셋 정보":{"파일 생성일자":"2020-11-26 17:46:25","데이터셋 상세설명":{"렉트좌표":{"아우터":[{}],"하의":[{}],"원피스":[{}],"상의":[{"X좌표":219.5,"Y좌표":0.5,"가로":326,"세로":429}]},"폴리곤좌표":{"아우터":[{}],"하의":[{}],"원피스":[{}],"상의":[{"Y좌표43":112.0,"Y좌표40":57.0,"Y좌표42":95.0,"Y좌표41":77.0,"X좌표39":286.0,"X좌표38":308.0,"X좌표37":336.0,"X좌표36":348.0,"X좌표35":328.0,"X좌표34":383.0,"X좌표33":444.0,"X좌표32":470.0,"X좌표31":488.0,"X좌표30":495.0,"Y좌표37":136.0,"Y좌표36":72.0,"X좌표8":252.0,"Y좌표39":85.0,"X좌표9":270.0,"Y좌표38":110.0,"Y좌표33":10.0,"Y좌표32":44.4,"Y좌표35":2.0,"Y좌표34":1.0,"Y좌표31":92.4,"Y좌표30":135.4,"X좌표2":228.0,"X좌표43":221.0,"X좌표3":240.0,"X좌표42":231.0,"X좌표41":243.0,"X좌표1":220.0,"X좌표40":256.0,"X좌표6":256.0,"X좌표7":252.0,"X좌표4":238.0,"X좌표5":252.0,"Y좌표26":322.0,"Y좌표25":335.0,"Y좌표28":208.4,"Y좌표9":414.0,"Y좌표27":260.0,"Y좌표22":373.0,"Y좌표21":392.0,"Y좌표24":337.0,"Y좌표23":352.0,"Y좌표20":406.0,"X좌표19":437.0,"X좌표18":416.0,"X좌표17":412.0,"X좌표16":404.0,"X좌표15":360.0,"X좌표14":319.0,"X좌표13":322.0,"X좌표12":316.0,"X좌표11":304.0,"Y좌표4":251.0,"X좌표10":287.0,"Y좌표3":191.0,"Y좌표2":159.0,"Y좌표1":109.0,"Y좌표8":408.0,"Y좌표7":371.0,"Y좌표29":179.4,"Y좌표6":345.0,"Y좌표5":300.0,"Y좌표15":403.0,"Y좌표14":390.0,"Y좌표17":418.0,"Y좌표16":430.0,"Y좌표11":410.0,"Y좌표10":417.0,"Y좌표13":342.4,"Y좌표12":407.4,"X좌표29":520.0,"X좌표28":523.0,"X좌표27":542.0,"X좌표26":546.0,"X좌표25":535.0,"X좌표24":504.0,"X좌표23":512.0,"X좌표22":504.0,"X좌표21":489.0,"X좌표20":458.0,"Y좌표19":417.0,"Y좌표18":382.0}]},"라벨링":{"스타일":[{"스타일":"키치"}],"아우터":[{}],"하의":[{}],"원피스":[{}],"상의":[{"기장":"롱","색상":"화이트","서브색상":"블랙","카테고리":"셔츠","옷깃":"테일러드칼라","디테일":["포켓"],"소매기장":"긴팔","소재":["우븐"],"프린트":["하트"],"핏":"노멀"}]}},"파일 번호":1315353,"파일 이름":"1 (27082).JPG"}}