{"이미지 정보":{"이미지 식별자":704092,"이미지 높이":1066,"이미지 파일명":"(312)IMG_1.jpg","이미지 너비":800},"데이터셋 정보":{"파일 생성일자":"2020-10-29 12:44:12","데이터셋 상세설명":{"렉트좌표":{"아우터":[{}],"하의":[{"X좌표":285.5,"Y좌표":662.5,"가로":214,"세로":395}],"원피스":[{}],"상의":[{"X좌표":232.5,"Y좌표":417.5,"가로":268,"세로":576}]},"폴리곤좌표":{"아우터":[{}],"하의":[{"Y좌표9":855.0,"X좌표17":302.0,"X좌표16":286.0,"X좌표15":297.0,"X좌표14":313.0,"X좌표13":317.0,"X좌표12":308.0,"X좌표11":388.0,"Y좌표4":754.0,"X좌표10":392.0,"Y좌표3":663.0,"Y좌표2":673.0,"Y좌표1":679.0,"Y좌표8":968.0,"Y좌표7":1058.0,"Y좌표6":1057.0,"Y좌표5":931.0,"Y좌표15":798.0,"Y좌표14":887.0,"X좌표8":424.0,"Y좌표17":679.0,"X좌표9":387.0,"Y좌표16":723.0,"Y좌표11":1058.0,"Y좌표10":944.0,"Y좌표13":972.0,"Y좌표12":1056.0,"X좌표2":410.0,"X좌표3":438.0,"X좌표1":306.0,"X좌표6":500.0,"X좌표7":430.0,"X좌표4":467.0,"X좌표5":495.0}],"원피스":[{}],"상의":[{"X좌표34":332.0,"X좌표33":309.0,"X좌표32":289.0,"X좌표31":252.0,"X좌표30":233.0,"X좌표8":463.0,"X좌표9":486.0,"Y좌표33":428.0,"Y좌표32":442.0,"Y좌표34":420.0,"Y좌표31":479.0,"Y좌표30":548.0,"X좌표2":351.0,"X좌표3":372.0,"X좌표1":336.0,"X좌표6":440.0,"X좌표7":465.0,"X좌표4":379.0,"X좌표5":409.0,"Y좌표26":921.0,"Y좌표25":952.0,"Y좌표28":748.0,"Y좌표9":754.0,"Y좌표27":833.0,"Y좌표22":984.0,"Y좌표21":828.0,"Y좌표24":994.0,"Y좌표23":991.0,"Y좌표20":648.0,"X좌표19":401.0,"X좌표18":379.0,"X좌표17":397.0,"X좌표16":424.0,"X좌표15":421.0,"X좌표14":419.0,"X좌표13":438.0,"X좌표12":479.0,"X좌표11":489.0,"Y좌표4":424.0,"X좌표10":501.0,"Y좌표3":461.0,"Y좌표2":449.0,"Y좌표1":418.0,"Y좌표8":623.0,"Y좌표7":570.0,"Y좌표29":663.0,"Y좌표6":495.0,"Y좌표5":443.0,"Y좌표15":613.0,"Y좌표14":695.0,"Y좌표17":533.0,"Y좌표16":560.0,"Y좌표11":933.0,"Y좌표10":885.0,"Y좌표13":800.0,"Y좌표12":907.0,"X좌표29":249.0,"X좌표28":263.0,"X좌표27":260.0,"X좌표26":277.0,"X좌표25":315.0,"X좌표24":334.0,"X좌표23":367.0,"X좌표22":397.0,"X좌표21":403.0,"X좌표20":405.0,"Y좌표19":584.0,"Y좌표18":501.0}]},"라벨링":{"스타일":[{"스타일":"스트리트"}],"아우터":[{}],"하의":[{"색상":"스카이블루","카테고리":"청바지","소재":["데님"],"프린트":["무지"],"핏":"스키니"}],"원피스":[{}],"상의":[{"기장":"롱","색상":"스카이블루","서브색상":"화이트","카테고리":"셔츠","옷깃":"셔츠칼라","디테일":["드롭숄더"],"소매기장":"7부소매","소재":["우븐"],"프린트":["스트라이프"],"핏":"노멀"}]}},"파일 번호":704092,"파일 이름":"(312)IMG_1.jpg"}}