{"이미지 정보":{"이미지 식별자":806720,"이미지 높이":1200,"이미지 파일명":"1-bl808(4)-유니(대행,S)6.23-3-IMG_6806.jpg","이미지 너비":800},"데이터셋 정보":{"파일 생성일자":"2020-11-03 10:34:09","데이터셋 상세설명":{"렉트좌표":{"아우터":[{}],"하의":[{"X좌표":347.5,"Y좌표":595.5,"가로":200,"세로":380}],"원피스":[{}],"상의":[{"X좌표":323.5,"Y좌표":387.5,"가로":180,"세로":334}]},"폴리곤좌표":{"아우터":[{}],"하의":[{"X좌표8":504.0,"X좌표9":497.0,"X좌표2":490.0,"X좌표3":512.0,"X좌표1":480.0,"X좌표6":548.0,"X좌표7":537.0,"X좌표4":528.0,"X좌표5":532.0,"Y좌표26":596.0,"Y좌표25":596.0,"Y좌표28":657.0,"Y좌표9":930.0,"Y좌표27":603.0,"Y좌표22":689.0,"Y좌표21":740.0,"Y좌표24":598.0,"Y좌표23":650.0,"Y좌표20":845.0,"X좌표19":380.0,"X좌표18":385.0,"X좌표17":400.0,"X좌표16":426.0,"X좌표15":424.0,"X좌표14":429.0,"X좌표13":425.0,"X좌표12":418.0,"X좌표11":434.0,"Y좌표4":867.0,"X좌표10":469.0,"Y좌표3":828.0,"Y좌표2":791.0,"Y좌표1":714.0,"Y좌표8":976.0,"Y좌표7":972.0,"Y좌표29":715.0,"Y좌표6":961.0,"Y좌표5":906.0,"Y좌표15":932.0,"Y좌표14":893.0,"Y좌표17":968.0,"Y좌표16":972.0,"Y좌표11":828.0,"Y좌표10":880.0,"Y좌표13":850.0,"Y좌표12":767.0,"X좌표29":480.0,"X좌표28":482.0,"X좌표27":470.0,"X좌표26":448.0,"X좌표25":405.0,"X좌표24":361.0,"X좌표23":351.0,"X좌표22":348.0,"X좌표21":349.0,"X좌표20":372.0,"Y좌표19":905.0,"Y좌표18":967.0}],"원피스":[{}],"상의":[{"Y좌표9":715.0,"Y좌표22":394.0,"Y좌표21":418.0,"Y좌표23":390.0,"Y좌표20":419.0,"X좌표19":418.0,"X좌표18":394.0,"X좌표17":355.0,"X좌표16":355.0,"X좌표15":334.0,"X좌표14":335.0,"X좌표13":324.0,"X좌표12":326.0,"X좌표11":365.0,"Y좌표4":478.0,"X좌표10":404.0,"Y좌표3":445.0,"Y좌표2":420.0,"Y좌표1":388.0,"Y좌표8":722.0,"Y좌표7":657.0,"Y좌표6":608.0,"Y좌표5":539.0,"Y좌표15":484.0,"Y좌표14":536.0,"X좌표8":488.0,"Y좌표17":421.0,"X좌표9":458.0,"Y좌표16":453.0,"Y좌표11":694.0,"Y좌표10":711.0,"Y좌표13":623.0,"Y좌표12":701.0,"X좌표23":473.0,"X좌표22":460.0,"X좌표2":484.0,"X좌표21":420.0,"X좌표3":497.0,"X좌표20":401.0,"X좌표1":468.0,"X좌표6":504.0,"Y좌표19":400.0,"X좌표7":496.0,"Y좌표18":406.0,"X좌표4":498.0,"X좌표5":500.0}]},"라벨링":{"스타일":[{"스타일":"레트로"}],"아우터":[{}],"하의":[{"기장":"발목","색상":"화이트","카테고리":"팬츠","소재":["스판덱스"],"프린트":["무지"],"핏":"스키니"}],"원피스":[{}],"상의":[{"기장":"롱","색상":"블루","서브색상":"핑크","카테고리":"블라우스","소매기장":"반팔","소재":["린넨"],"프린트":["도트"],"넥라인":"라운드넥","핏":"루즈"}]}},"파일 번호":806720,"파일 이름":"1-bl808(4)-유니(대행,S)6.23-3-IMG_6806.jpg"}}